{
  "rab": [
    {
      "komponen": 55,
      "akun": "[532111] Belanja Modal Peralatan dan Mesin",
      "detil": "Ford Transit Sprinter",
      "rincian": 1,
      "mata_uang_harga": "USD",
      "harga": 59811,
      "mata_uang_jumlah": "IDR",
      "jumlah": 897165
    },
    {
      "komponen": 55,
      "akun": "[532111] Belanja Modal Peralatan dan Mesin",
      "detil": "Ford Transit Sprinter",
      "rincian": 1,
      "mata_uang_harga": "USD",
      "harga": 59811,
      "mata_uang_jumlah": "IDR",
      "jumlah": 897165
    },
    {
      "komponen": 55,
      "akun": "[532111] Belanja Modal Peralatan dan Mesin",
      "detil": "Ford Transit Sprinter",
      "rincian": 1,
      "mata_uang_harga": "USD",
      "harga": 59811,
      "mata_uang_jumlah": "IDR",
      "jumlah": 897165
    },
    {
      "komponen": 55,
      "akun": "[532111] Belanja Modal Peralatan dan Mesin",
      "detil": "Ford Transit Sprinter",
      "rincian": 1,
      "mata_uang_harga": "USD",
      "harga": 59811,
      "mata_uang_jumlah": "IDR",
      "jumlah": 897165
    }
  ]
}